{
"2025": {
    "rankings": {
        "Overall Record": "6-4",
        "Conference Standings": "#0",
        "AP Poll": "N/A",
        "KenPom": "#20",
        "NET Rankings": "#30",
        "Evan Miya": "#26",
        "Barttorvik": "#25",
        "Bracketology": "No. 6 Seed",
        "AP Top 25 Record": "0-4"
    },
    "stats": {
        "Offensive Rating": { "value": "119.0", "rank": "34" },
        "Defensive Rating": { "value": "96.9", "rank": "22" },
        "Net Rating": { "value": "22.06", "rank": "20" },
        "Pace": { "value": "71.2", "rank": "103" },
        "Offensive TOV%": { "value": "14.7", "rank": "46" },
        "Defensive TOV%": { "value": "15.5", "rank": "282" },
        "O3P%": { "value": "31.9", "rank": "229" },
        "O2P%": { "value": "59.2", "rank": "32" },
        "OFT%": { "value": "75.0", "rank": "82" },
        "D3P%": { "value": "29.5", "rank": "53" },
        "D2P%": { "value": "45.4", "rank": "29" },
        "DFT%": { "value": "66.4", "rank": "39" }

    }
},

"2024": {
    "rankings": {
        "Overall Record": "24-12",
        "Conference Standings": "#6",
        "AP Poll": "#12",
        "KenPom": "#16",
        "NET Rankings": "#14",
        "Evan Miya": "#28",
        "Barttorvik": "#13",
        "Bracketology": "No. 3 Seed",
        "AP Top 25 Record": "8-5"
    },
    "stats": {
        "Offensive Rating": { "value": "123.7", "rank": "10" },
        "Defensive Rating": { "value": "99.2", "rank": "51" },
        "Net Rating": { "value": "+24.54", "rank": "16" },
        "Pace": { "value": "73.7", "rank": "9" },
        "Offensive TOV%": { "value": "15.0", "rank": "39" },
        "Defensive TOV%": { "value": "14.1", "rank": "338" },
        "O3P%": { "value": "37.5", "rank": "24" },
        "O2P%": { "value": "55.6", "rank": "34" },
        "OFT%": { "value": "73.1", "rank": "131" },
        "D3P%": { "value": "30.5", "rank": "20" },
        "D2P%": { "value": "53.9", "rank": "296" },
        "DFT%": { "value": "71.7", "rank": "120" }
    }
}
}























